<?xml version="1.0" encoding="UTF-8" standalone="no"?><factura id="comprobante" version="1.1.0"><infoTributaria><ambiente>2</ambiente><tipoEmision>1</tipoEmision><razonSocial>Almacenes Juan Eljuri Cia. LTDA.</razonSocial><nombreComercial>Almacenes Juan Eljuri Cia. LTDA.</nombreComercial><ruc>0190007510001</ruc><claveAcceso>1505202001019000751000120010990000005090000050911</claveAcceso><codDoc>01</codDoc><estab>001</estab><ptoEmi>099</ptoEmi><secuencial>000000509</secuencial><dirMatriz>Av. Gil Ramírez Dávalos y Armenillas</dirMatriz></infoTributaria><infoFactura><fechaEmision>15/05/2020</fechaEmision><dirEstablecimiento>La Taberna Kennedy Norte (Guayaquil) Av. Gil Ramírez Dávalos y Armenillas</dirEstablecimiento><obligadoContabilidad>SI</obligadoContabilidad><tipoIdentificacionComprador>05</tipoIdentificacionComprador><razonSocialComprador>jonathan merizalde</razonSocialComprador><identificacionComprador>0905828315</identificacionComprador><direccionComprador>Boyaca, Guayaquil, ECU</direccionComprador><totalSinImpuestos>147.81</totalSinImpuestos><totalDescuento>0.00</totalDescuento><totalConImpuestos><totalImpuesto><codigo>2</codigo><codigoPorcentaje>2</codigoPorcentaje><descuentoAdicional>0.00</descuentoAdicional><baseImponible>147.81</baseImponible><valor>17.73</valor></totalImpuesto></totalConImpuestos><propina>0.00</propina><importeTotal>165.54</importeTotal><pagos><pago><formaPago>20</formaPago><total>165.54</total><plazo>0</plazo><unidadTiempo>DIAS</unidadTiempo></pago></pagos></infoFactura><detalles><detalle><codigoPrincipal>10063532</codigoPrincipal><descripcion>TEQUILA CUERVO ESPECIAL SILVER 750 ML</descripcion><cantidad>2.00</cantidad><precioUnitario>44.20</precioUnitario><descuento>0.00</descuento><precioTotalSinImpuesto>88.40</precioTotalSinImpuesto><impuestos><impuesto><codigo>2</codigo><codigoPorcentaje>2</codigoPorcentaje><tarifa>12.00</tarifa><baseImponible>88.40</baseImponible><valor>10.61</valor></impuesto></impuestos></detalle><detalle><codigoPrincipal>10064219</codigoPrincipal><descripcion>ENERGIZANTE 440 LATA 269ML</descripcion><cantidad>3.00</cantidad><precioUnitario>0.89</precioUnitario><descuento>0.00</descuento><precioTotalSinImpuesto>2.67</precioTotalSinImpuesto><impuestos><impuesto><codigo>2</codigo><codigoPorcentaje>2</codigoPorcentaje><tarifa>12.00</tarifa><baseImponible>2.67</baseImponible><valor>0.32</valor></impuesto></impuestos></detalle><detalle><codigoPrincipal>10091069</codigoPrincipal><descripcion>LATITUD CERO ANTISANA 5L</descripcion><cantidad>2.00</cantidad><precioUnitario>26.77</precioUnitario><descuento>0.00</descuento><precioTotalSinImpuesto>53.54</precioTotalSinImpuesto><impuestos><impuesto><codigo>2</codigo><codigoPorcentaje>2</codigoPorcentaje><tarifa>12.00</tarifa><baseImponible>53.54</baseImponible><valor>6.42</valor></impuesto></impuestos></detalle><detalle><codigoPrincipal>20000154</codigoPrincipal><descripcion>TRANSPORTE - SERV VARIOS TABERNAS</descripcion><cantidad>1.00</cantidad><precioUnitario>3.20</precioUnitario><descuento>0.00</descuento><precioTotalSinImpuesto>3.20</precioTotalSinImpuesto><impuestos><impuesto><codigo>2</codigo><codigoPorcentaje>2</codigoPorcentaje><tarifa>12.00</tarifa><baseImponible>3.20</baseImponible><valor>0.38</valor></impuesto></impuestos></detalle></detalles></factura>